Metadata-Version: 2.1
Name: ifc-data-checker
Version: 1.0.1
Summary: The IFC Data Checker can validate rules on an ifc model.
Home-page: https://github.com/idibau/ifc-data-checker
Author: Dominik Fringeli
Author-email: dominik.fringeli@students.fhnw.ch
License: UNKNOWN
Platform: UNKNOWN
Classifier: Programming Language :: Python :: 3
Classifier: License :: OSI Approved :: MIT License
Classifier: Operating System :: OS Independent
Classifier: Environment :: Console
Requires-Python: >=3.8
Requires-Dist: pyyaml
Requires-Dist: jsonschema
